torch_sgld/__init__.py
torch_sgld/lr_scheduler.py
torch_sgld/sgld.py
torch_sgld-0.1.0.dist-info/LICENSE
torch_sgld-0.1.0.dist-info/METADATA
torch_sgld-0.1.0.dist-info/WHEEL
torch_sgld-0.1.0.dist-info/top_level.txt
torch_sgld-0.1.0.dist-info/RECORD
